<?xml version="1.0" encoding="utf-8"?>
<odoo>
	<record id="report_mw_tax_report_tt02" model="ir.ui.view">
		<field name="name">report_mw_tax_report_tt02</field>
		<field name="model">mw.tax.report.tt02</field>
		<field name="type">form</field>
		<field name="arch" type="xml">
			<form>
				<group>
					<group>
						<field name="date_start"/>
						<field name="date_end"/>
					</group>
					<group>
					</group>
				</group>
				<footer>
					<button icon="fa-times" special="cancel" string="Хаах" colspan="2"/>
					<button name="action_mw_tax_report_tt02_export" string="Татах" type="object" colspan="2"
						class="oe_highlight" icon="fa-file-excel-o"/>
				</footer>
			</form>
		</field>
	</record>

	<record id="action_report_mw_tax_report_tt02" model="ir.actions.act_window">
		<field name="name">ААНОАТ-ын тайлан /ТТ-02/</field>
		<field name="res_model">mw.tax.report.tt02</field>
		<field name="view_mode">form</field>
		<field name="view_id" ref="report_mw_tax_report_tt02"/>
		<field name="target">new</field>
	</record>
</odoo>
	 